{
  "last_updated": "2025-11-14T01:12:11.084828Z",
  "total_fire_count": 1800,
  "date_range": {
    "start": "2025-11-06",
    "end": "2025-11-13"
  },
  "top_districts": [
    {
      "state": "Punjab",
      "district": "Firozpur",
      "total_fires": 165
    },
    {
      "state": "Punjab",
      "district": "Moga",
      "total_fires": 146
    },
    {
      "state": "Punjab",
      "district": "Ludhiana",
      "total_fires": 139
    },
    {
      "state": "Punjab",
      "district": "Tarn Taran",
      "total_fires": 138
    },
    {
      "state": "Punjab",
      "district": "Sangrur",
      "total_fires": 133
    },
    {
      "state": "Punjab",
      "district": "Sri Muktsar Sahib",
      "total_fires": 127
    },
    {
      "state": "Punjab",
      "district": "Bathinda",
      "total_fires": 102
    },
    {
      "state": "Haryana",
      "district": "Jind",
      "total_fires": 97
    },
    {
      "state": "Punjab",
      "district": "Fazilka",
      "total_fires": 90
    },
    {
      "state": "Punjab",
      "district": "Mansa",
      "total_fires": 86
    },
    {
      "state": "Punjab",
      "district": "Patiala",
      "total_fires": 57
    },
    {
      "state": "Punjab",
      "district": "Jalandhar",
      "total_fires": 56
    },
    {
      "state": "Haryana",
      "district": "Hisar",
      "total_fires": 52
    },
    {
      "state": "Punjab",
      "district": "Faridkot",
      "total_fires": 51
    },
    {
      "state": "Haryana",
      "district": "Fatehabad",
      "total_fires": 37
    },
    {
      "state": "Haryana",
      "district": "Sonipat",
      "total_fires": 36
    },
    {
      "state": "Punjab",
      "district": "Amritsar",
      "total_fires": 32
    },
    {
      "state": "Haryana",
      "district": "Rohtak",
      "total_fires": 30
    },
    {
      "state": "Punjab",
      "district": "Kapurthala",
      "total_fires": 29
    },
    {
      "state": "Haryana",
      "district": "Kaithal",
      "total_fires": 28
    }
  ],
  "state_totals": {
    "punjab": 1421,
    "haryana": 379
  }
}