{
  "last_updated": "2025-12-29T12:35:34.565009Z",
  "total_fire_count": 131,
  "date_range": {
    "start": "2025-12-22",
    "end": "2025-12-29"
  },
  "top_districts": [
    {
      "state": "Punjab",
      "district": "Mansa",
      "total_fires": 23
    },
    {
      "state": "Haryana",
      "district": "Faridabad",
      "total_fires": 20
    },
    {
      "state": "Haryana",
      "district": "Sonipat",
      "total_fires": 10
    },
    {
      "state": "Punjab",
      "district": "Patiala",
      "total_fires": 9
    },
    {
      "state": "Haryana",
      "district": "Hisar",
      "total_fires": 9
    },
    {
      "state": "Haryana",
      "district": "Jhajjar",
      "total_fires": 5
    },
    {
      "state": "Punjab",
      "district": "Jalandhar",
      "total_fires": 5
    },
    {
      "state": "Haryana",
      "district": "Bhiwani",
      "total_fires": 5
    },
    {
      "state": "Punjab",
      "district": "Amritsar",
      "total_fires": 4
    },
    {
      "state": "Punjab",
      "district": "Ludhiana",
      "total_fires": 4
    },
    {
      "state": "Punjab",
      "district": "Shahid Bhagat Singh Nagar",
      "total_fires": 4
    },
    {
      "state": "Haryana",
      "district": "Jind",
      "total_fires": 4
    },
    {
      "state": "Haryana",
      "district": "Ambala",
      "total_fires": 3
    },
    {
      "state": "Haryana",
      "district": "Rohtak",
      "total_fires": 3
    },
    {
      "state": "Punjab",
      "district": "Fatehgarh Sahib",
      "total_fires": 3
    },
    {
      "state": "Punjab",
      "district": "Bathinda",
      "total_fires": 2
    },
    {
      "state": "Haryana",
      "district": "Panipat",
      "total_fires": 2
    },
    {
      "state": "Haryana",
      "district": "Yamunanagar",
      "total_fires": 2
    },
    {
      "state": "Punjab",
      "district": "Hoshiarpur",
      "total_fires": 2
    },
    {
      "state": "Punjab",
      "district": "Barnala",
      "total_fires": 1
    }
  ],
  "state_totals": {
    "punjab": 63,
    "haryana": 68
  }
}