{
  "last_updated": "2026-02-11T12:58:31.081098Z",
  "total_fire_count": 237,
  "date_range": {
    "start": "2026-02-04",
    "end": "2026-02-11"
  },
  "top_districts": [
    {
      "state": "Punjab",
      "district": "Gurdaspur",
      "total_fires": 35
    },
    {
      "state": "Punjab",
      "district": "Hoshiarpur",
      "total_fires": 19
    },
    {
      "state": "Punjab",
      "district": "Mansa",
      "total_fires": 18
    },
    {
      "state": "Haryana",
      "district": "Bhiwani",
      "total_fires": 16
    },
    {
      "state": "Haryana",
      "district": "Faridabad",
      "total_fires": 15
    },
    {
      "state": "Haryana",
      "district": "Hisar",
      "total_fires": 15
    },
    {
      "state": "Haryana",
      "district": "Rohtak",
      "total_fires": 15
    },
    {
      "state": "Haryana",
      "district": "Jhajjar",
      "total_fires": 10
    },
    {
      "state": "Haryana",
      "district": "Sonipat",
      "total_fires": 10
    },
    {
      "state": "Haryana",
      "district": "Panipat",
      "total_fires": 9
    },
    {
      "state": "Punjab",
      "district": "Bathinda",
      "total_fires": 6
    },
    {
      "state": "Punjab",
      "district": "Kapurthala",
      "total_fires": 6
    },
    {
      "state": "Punjab",
      "district": "Fatehgarh Sahib",
      "total_fires": 5
    },
    {
      "state": "Haryana",
      "district": "Jind",
      "total_fires": 5
    },
    {
      "state": "Haryana",
      "district": "Palwal",
      "total_fires": 4
    },
    {
      "state": "Punjab",
      "district": "Sahibzada Ajit Singh Nag*",
      "total_fires": 4
    },
    {
      "state": "Punjab",
      "district": "Rupnagar",
      "total_fires": 4
    },
    {
      "state": "Haryana",
      "district": "Karnal",
      "total_fires": 4
    },
    {
      "state": "Haryana",
      "district": "Kaithal",
      "total_fires": 4
    },
    {
      "state": "Punjab",
      "district": "Amritsar",
      "total_fires": 4
    }
  ],
  "state_totals": {
    "punjab": 117,
    "haryana": 120
  }
}